{
"type": "FeatureCollection",
"name": "racks",
"features": [
{ "type": "Feature", "properties": { "comments": "Bike Centre", "capacity": null, "zone": "Dalhousie University - Sexton Campus" }, "geometry": { "type": "Point", "coordinates": [ -63.591043904148087, 44.636350548379532 ] } },
{ "type": "Feature", "properties": { "comments": "Killam Library", "capacity": null, "zone": "Dalhousie University - Sexton Campus" }, "geometry": { "type": "Point", "coordinates": [ -63.590663033880709, 44.637180451562607 ] } },
{ "type": "Feature", "properties": { "comments": "Student Union Building", "capacity": null, "zone": "Dalhousie University - Sexton Campus" }, "geometry": { "type": "Point", "coordinates": [ -63.589480064020094, 44.636930328848806 ] } },
{ "type": "Feature", "properties": { "comments": "Management", "capacity": null, "zone": "Dalhousie University - Sexton Campus" }, "geometry": { "type": "Point", "coordinates": [ -63.588463541132541, 44.637266024174565 ] } },
{ "type": "Feature", "properties": { "comments": "Computer Science", "capacity": null, "zone": "Dalhousie University - Sexton Campus" }, "geometry": { "type": "Point", "coordinates": [ -63.587251147946859, 44.637589280052786 ] } },
{ "type": "Feature", "properties": { "comments": "Wallace McCain Learning Commons (WMLC)", "capacity": null, "zone": "Dalhousie University - Sexton Campus" }, "geometry": { "type": "Point", "coordinates": [ -63.59369797304749, 44.636931969472926 ] } },
{ "type": "Feature", "properties": { "comments": "Dalhousie Medicine", "capacity": null, "zone": "Dalhousie University - Sexton Campus" }, "geometry": { "type": "Point", "coordinates": [ -63.584084014603761, 44.639096904583184 ] } },
{ "type": "Feature", "properties": { "comments": "Collaborative Health Education Building (CHEB)", "capacity": null, "zone": "Dalhousie University - Sexton Campus" }, "geometry": { "type": "Point", "coordinates": [ -63.582532662115177, 44.639335694914479 ] } },
{ "type": "Feature", "properties": { "comments": "Marion McCain Building", "capacity": null, "zone": "Dalhousie University - Sexton Campus" }, "geometry": { "type": "Point", "coordinates": [ -63.589628458342212, 44.63729956154031 ] } },
{ "type": "Feature", "properties": { "comments": "Schulich School of Law", "capacity": null, "zone": "Dalhousie University - Sexton Campus" }, "geometry": { "type": "Point", "coordinates": [ -63.587818294304761, 44.637953707025105 ] } },
{ "type": "Feature", "properties": { "comments": "Nova Scotia Archives", "capacity": null, "zone": "Dalhousie University - Sexton Campus" }, "geometry": { "type": "Point", "coordinates": [ -63.586130909841984, 44.6378044143271 ] } },
{ "type": "Feature", "properties": { "comments": "Shirreff Hall", "capacity": null, "zone": "Dalhousie University - Sexton Campus" }, "geometry": { "type": "Point", "coordinates": [ -63.594334005712405, 44.634649217003918 ] } },
{ "type": "Feature", "properties": { "comments": "Dalplex", "capacity": null, "zone": "Dalhousie University - Sexton Campus" }, "geometry": { "type": "Point", "coordinates": [ -63.592620159767179, 44.634243869300946 ] } },
{ "type": "Feature", "properties": { "comments": "Henry Hicks / University Club", "capacity": null, "zone": "Dalhousie University - Sexton Campus" }, "geometry": { "type": "Point", "coordinates": [ -63.592539036884318, 44.63609827136068 ] } },
{ "type": "Feature", "properties": { "comments": "King's Library", "capacity": null, "zone": "Dalhousie University - Sexton Campus" }, "geometry": { "type": "Point", "coordinates": [ -63.594041136549301, 44.637533531848391 ] } },
{ "type": "Feature", "properties": { "comments": "Dunn Building", "capacity": null, "zone": "Dalhousie University - Sexton Campus" }, "geometry": { "type": "Point", "coordinates": [ -63.593141342404756, 44.637927259236825 ] } },
{ "type": "Feature", "properties": { "comments": "Howe Hall", "capacity": null, "zone": "Dalhousie University - Sexton Campus" }, "geometry": { "type": "Point", "coordinates": [ -63.592039575937015, 44.638688608549842 ] } },
{ "type": "Feature", "properties": { "comments": "Dentistry", "capacity": null, "zone": "Dalhousie University - Sexton Campus" }, "geometry": { "type": "Point", "coordinates": [ -63.584834633581359, 44.638567504173913 ] } },
{ "type": "Feature", "properties": { "comments": "Tupper", "capacity": null, "zone": "Dalhousie University - Sexton Campus" }, "geometry": { "type": "Point", "coordinates": [ -63.584176870242608, 44.639764269560146 ] } },
{ "type": "Feature", "properties": { "comments": "Life Sciences Research Institute", "capacity": null, "zone": "Dalhousie University - Sexton Campus" }, "geometry": { "type": "Point", "coordinates": [ -63.582877436432653, 44.640016102035077 ] } },
{ "type": "Feature", "properties": { "comments": "Prince Hall", "capacity": null, "zone": "King's College" }, "geometry": { "type": "Point", "coordinates": [ -63.595225204410866, 44.637733759093017 ] } }
]
}
